{
    "810471003855519754": {
        "name": "Chaudard",
        "tickets": {
            "ticket-1073": 1628181893000,
            "ticket-1080": 1628463465627,
            "ticket-1083": 1628502717425
        }
    },
    "272361822965858308": {
        "name": "RedXxSpookyyy |OnlyRedXx.tv|",
        "tickets": {
            "ticket-1074": 1628109030977,
            "ticket-1077": 1628434193000
        }
    },
    "222027506746785793": {
        "name": "Rachellp",
        "tickets": {
            "ticket-1075": 1628434193000,
            "ticket-1076": 1628434193000
        }
    },
    "278874425091293184": {
        "name": "JokerMatlej",
        "tickets": {
            "ticket-1083": 1628502695012
        }
    }
}